flatyplus/YTclip.py
flatyplus/control.py
flatyplus/interframe.py
flatyplus/sdxl_diffuser.py
flatyplus/video.py
flatyplus-0.1.2.dist-info/LICENSE
flatyplus-0.1.2.dist-info/METADATA
flatyplus-0.1.2.dist-info/WHEEL
flatyplus-0.1.2.dist-info/top_level.txt
flatyplus-0.1.2.dist-info/RECORD
